[
  {
    "title": "すまん、この令和の時代に“PCで5ch”やってるクソジジイってまだいるのか？",
    "thread_id": "1769247084"
  },
  {
    "title": "中国軍トップ、逮捕。",
    "thread_id": "1769267436"
  },
  {
    "title": "【世論】高市、痛恨のミス！冒頭解散を支持する２１．４％のみ！",
    "thread_id": "1769267452"
  },
  {
    "title": "【悲報】安倍昭恵山上徹也は私に謝罪してないんだけど",
    "thread_id": "1769263426"
  },
  {
    "title": "トランプ、4月に訪中 素晴らしい関係を保っている 習近平は国賓として年末に訪米 米中蜜月時代に突入",
    "thread_id": "1769189216"
  },
  {
    "title": "Z李、政府のTikTok工作部署を暴露してしまう。",
    "thread_id": "1769167164"
  },
  {
    "title": "そこまでカワイイ顔じゃないが、魅力的なブサかわいい顔 誰を思い浮かべた？",
    "thread_id": "1769270899"
  },
  {
    "title": "【悲報】トランプカナダが中国と協定を結んだ場合、米国に輸入されるすべてのカナダ製品に対して即座に100%の関税を課す",
    "thread_id": "1769265018"
  },
  {
    "title": "ナイトスクープ、大炎上！！今から嫌儲でも大炎上予定",
    "thread_id": "1769267727"
  },
  {
    "title": "ヨーロッパ人トランプはヨーロッパの敵51%友人8%",
    "thread_id": "1769223519"
  },
  {
    "title": "なんで同じスレが乱立してるの？",
    "thread_id": "1769266443"
  },
  {
    "title": "創価を叩くと激怒するケンモメン、急増！",
    "thread_id": "1769064593"
  },
  {
    "title": "ハイタッチは日本人しか使ってない。欧米ではハイファイブと呼んでいた",
    "thread_id": "1769166187"
  },
  {
    "title": "小林よしのり日本はもう将来性がないと判断されたんだが、サナ活ファンは何にも考えてなくて、高市がドラム叩いたから喜んでるだけだ",
    "thread_id": "1769270003"
  },
  {
    "title": "今日の給食テーマは、昔の給食の給食だよ～！ いい加減にしろ、ふざけるな´・ω・`",
    "thread_id": "1769236482"
  },
  {
    "title": "【悲報】高市早苗金正恩さんと無条件で会談がしたい",
    "thread_id": "1769268346"
  },
  {
    "title": "【動画】豊田章男チョレイ！⇨トヨタ社員ザッ一斉立ち上がる アメリカ人がビビり散らかす",
    "thread_id": "1769226004"
  },
  {
    "title": "【画像】昔のダイソーの雰囲気",
    "thread_id": "1769269735"
  },
  {
    "title": "ヽ´ん`新潟市は雪積もらない=よくこういう嘘つきいるでしょ？",
    "thread_id": "1769236372"
  },
  {
    "title": "【画像】菊池姫奈21とかいう顔そこそこ・カラダ100点ケンモメンお嫁さん候補の魅力",
    "thread_id": "1769262904"
  },
  {
    "title": "高須克弥顔をさらせ！ 馬鹿。",
    "thread_id": "1769271286"
  },
  {
    "title": "【悲報】原口一博議員、チームみらいに捨て台詞を吐いて去る",
    "thread_id": "1769149852"
  },
  {
    "title": "【動画】これにガチギレてしまう人は子供を持たない方がいいらしい",
    "thread_id": "1769260093"
  },
  {
    "title": "U23アジアカップ決勝 日本VS中国 0:00キックオフ",
    "thread_id": "1769266710"
  },
  {
    "title": "【速報】2008、2009年くらいのニコニコ動画のワクワク感が異常だと話題に",
    "thread_id": "1769249664"
  },
  {
    "title": "もし戦争になって、Z世代が徴兵反対！と言い出したらどうする？俺は反対デモをバカにしに行く",
    "thread_id": "1769188453"
  },
  {
    "title": "【高市】 中道の野田代表、他の各党首からフルボッコにされる",
    "thread_id": "1769260773"
  },
  {
    "title": "ACE COMBAT™7: SKIES UNKNOWN世界累計販売本数700万本突破！シリーズ世界累計販売本数は 2,100 万本に到達！",
    "thread_id": "1769252587"
  },
  {
    "title": "【悲報】MBS、番組内で自民・維新・参政党を強くて怖い日本に分類したことを謝罪",
    "thread_id": "1769156613"
  },
  {
    "title": "そういえば、ＶＯＷって本あったよな。",
    "thread_id": "1769266161"
  },
  {
    "title": "おすすめのシュミレーションSRPG、何かある？",
    "thread_id": "1769224175"
  },
  {
    "title": "真夏の夜の淫夢",
    "thread_id": "1769252370"
  },
  {
    "title": "安倍晋三さんが殺された時、その場で統一協会のキャンペーンをやっていた",
    "thread_id": "1769255153"
  },
  {
    "title": "【うぉぉぉぉ！！】イーロン・マスク氏人型ロボットは2027年に販売、人口を上回る数になる",
    "thread_id": "1769260543"
  },
  {
    "title": "【悲報】高市首相TM文書なるものに接していませんが、私自身に関する記載は明らかに誤っている",
    "thread_id": "1769263944"
  },
  {
    "title": "【悲報】ぼくの作ったペペロンチーノ、やはり味がしない。理由がわからない。",
    "thread_id": "1769222672"
  },
  {
    "title": "【あの日見た高市の増税悲報】年収650万円底辺弱者男性36だけど結婚したいこのスペックでできるか木炭のない意見を教えてくれ",
    "thread_id": "1769251002"
  },
  {
    "title": "【画像】貴殿らはこの牡蠣カバ丼定食2480円税込にいくら払える？",
    "thread_id": "1769270288"
  },
  {
    "title": "【画像】ちいかわたちが″ぽっちゃり″体型になった可愛すぎるヌイグルミが発売",
    "thread_id": "1769259317"
  },
  {
    "title": "麻生節炸裂昔は立憲共産党と言った時代もあったが、立憲公明党という政党が新しく出てきた。チュウカクみたいな名前だったか",
    "thread_id": "1769254461"
  },
  {
    "title": "医師のホロライブファンこの例えがあってるかわからないけどアンチはがん細胞みたいなものヽ´ん`はがん細胞",
    "thread_id": "1769225457"
  },
  {
    "title": "政府関係者小野田大臣はネットを見て、世間で問題になっていることを拾えているかチェックしている",
    "thread_id": "1769217684"
  },
  {
    "title": "中国人おい、なぜ日本人は中国人を見分けられるんだ？？？",
    "thread_id": "1769251789"
  },
  {
    "title": "パパさん娘の\"純潔\"を守りたいです。どうすればいいですか；；",
    "thread_id": "1769192869"
  },
  {
    "title": "ナンミョメンケンモで創価を支持する謎の勢力、発狂",
    "thread_id": "1769212265"
  },
  {
    "title": "ヽ´ん`！三ヽ´`女性と目が合い、舌を出し、この女性と同じ列車に乗り、駅に着くと、声をかける男性発生",
    "thread_id": "1769237651"
  },
  {
    "title": "東京科学大教授高市総理は野党と戦ってるのではない、麻生と戦ってる",
    "thread_id": "1769233596"
  },
  {
    "title": "またいつか派ともう来るな派に溝 そもそも民間が借りて見たい人が見てるだけで反対派が口挟めないだろ",
    "thread_id": "1769250046"
  },
  {
    "title": "【速報】ぼく42国家資格・ITパスポートに合格するwvw 高市も祝意か",
    "thread_id": "1769249993"
  },
  {
    "title": "【高市悲報】参政党のポスター英語で高らかにアピール",
    "thread_id": "1769218861"
  },
  {
    "title": "黒髪清楚の冷酷美少女を助けたら 、俺と二人きりの時だけデレるようになったらどうする？",
    "thread_id": "1769257762"
  },
  {
    "title": "フリーレンの荒らしは特定のBEをNGにさせるためにやってんのか",
    "thread_id": "1769188703"
  },
  {
    "title": "推しの子あの、第3期放送中です・・・",
    "thread_id": "1769241996"
  },
  {
    "title": "【悲報】高市国旗損壊罪、必ず実現",
    "thread_id": "1769251919"
  },
  {
    "title": "子供6人の大家族アベ家の長男、探偵ナイトスクープに出演ずっと下5人の世話をしてるから、世話される側になりたい大炎上",
    "thread_id": "1769210660"
  },
  {
    "title": "⭐今期アニメ総合⭐",
    "thread_id": "1769271191"
  },
  {
    "title": "コヒーがぶ飲みして熟睡できないまま一日中布団で微睡んでるのも心地良い",
    "thread_id": "1769254600"
  },
  {
    "title": "【ドアコック】埼京線で突如ジョーカー発生！車内にいた人が、非常用ドアコックを操作し扉ドアを開放。５００人が線路に脱出！",
    "thread_id": "1769177061"
  },
  {
    "title": "【衆議院選挙】中道改革連合、大阪府は切り捨てるほとんど立候補者がいない",
    "thread_id": "1769239668"
  },
  {
    "title": "アパート大家家賃1年分滞納されている部屋に入ってみた→結果",
    "thread_id": "1769256803"
  },
  {
    "title": "嘘喰い作者、８８万の高級パソコンを買う",
    "thread_id": "1769251785"
  },
  {
    "title": "【報道特集】TM文書 自民党アレは怪文書。無視無視⇐マジかよ",
    "thread_id": "1769248946"
  },
  {
    "title": "木村拓哉と萩原聖人、和解",
    "thread_id": "1769258140"
  },
  {
    "title": "黒髪清楚の冷酷美少女を助けたら、 俺と二人きりの時だけデレるようになったらどうする？",
    "thread_id": "1769257876"
  },
  {
    "title": "自民党小野寺大臣日本は移民を受け入れないと回らない",
    "thread_id": "1769239703"
  },
  {
    "title": "黒髪清楚の冷酷美少女を助けたら 、俺と二人きりの時だけデレるようになったらどうする？",
    "thread_id": "1769257813"
  },
  {
    "title": "女の子男が9割国会議員ってアホかよ。犯罪者の9割占める性別が国の運営を独占する、だから衰退するのよ",
    "thread_id": "1769257420"
  },
  {
    "title": "特攻隊員の遺書、ワンコインで売られてしまう。散ってなお愛国ポルノとして消費搾取される戦死者に涙",
    "thread_id": "1769216188"
  },
  {
    "title": "【動画】最近このタイプの激辛ラーメンが流行ってるみたいだけどこれ辛い物苦手な人は無理だろ",
    "thread_id": "1769253538"
  },
  {
    "title": "【画像】貴殿らはこの鶏の発酵唐揚げ定食1610円税込にいくら払える？",
    "thread_id": "1769249470"
  },
  {
    "title": "【悲報】聖帝語録スクリプト、なぜか今期アニメスレを狙い撃ちで荒らしまくってしまう",
    "thread_id": "1769269767"
  },
  {
    "title": "【経済オンチ】公明党のゆってる政府系ファンドってホント意味不明",
    "thread_id": "1769234345"
  },
  {
    "title": "引きこもり等対策交付金、7割カット",
    "thread_id": "1769266989"
  },
  {
    "title": "アメリカ、これからは本土防衛が最優先 同盟国には防衛費GDP比5%以上を要求",
    "thread_id": "1769231606"
  },
  {
    "title": "石原裕次郎享年52って酒の飲み過ぎでなくなったの？",
    "thread_id": "1769169582"
  },
  {
    "title": "黒髪清楚の 冷酷美少女を助けたら、俺と二人きりの時だけデレるようになったらどうする？",
    "thread_id": "1769256755"
  },
  {
    "title": "高市早苗、視覚障がい者から選挙権はく奪へw",
    "thread_id": "1769258380"
  },
  {
    "title": "【悲報】美容師50歳のオッサンでも薄目のサングラスをかけると20代雰囲気イケメンになるぞ!ソースは俺→ではご覧ください",
    "thread_id": "1769244045"
  },
  {
    "title": "ヽ^ん^レギュラー135円！？ここで入れるか！ 結果",
    "thread_id": "1769214305"
  },
  {
    "title": "シフターの箱を開けた",
    "thread_id": "1769256047"
  },
  {
    "title": "黒髪清楚の冷酷美少女を助 けたら、俺と二人きりの時だけデレるようになったらどうする？",
    "thread_id": "1769257476"
  },
  {
    "title": "小泉進次郎今回の選挙で訴えるのは混迷か、再建か。中道改革連合は混迷の道を辿る。我々は再建する。中道が勝ったら中国が喜ぶ",
    "thread_id": "1769260013"
  },
  {
    "title": "トランプNATOってアフガンで後方支援しかしなかったチキンだろ",
    "thread_id": "1769255808"
  },
  {
    "title": "立憲は方針180度変えたのに、支持してたバカは今まで立憲に騙されたという認識が全くないの面白いよな",
    "thread_id": "1769250981"
  },
  {
    "title": "【謎】オクトパストラベラーこのスクエニの今の実力が分かる全力のクソゲーが大絶賛だった理由",
    "thread_id": "1769166055"
  },
  {
    "title": "野田佳彦選挙で統一教会問題、TM報告書を争点にする。有田芳生に特命を与えた",
    "thread_id": "1769218477"
  },
  {
    "title": "俺いくら高市人気がすごくても公明もいなくなったし、自民党ボロ負けだろw結果",
    "thread_id": "1769216182"
  },
  {
    "title": "【悲報】高市早苗、チームみらい安野貴博に論破される",
    "thread_id": "1769255860"
  },
  {
    "title": "株価7000円、円高デフレ、就職氷河期悪夢の民主党政権とは一体なんだったのか。なぜ特定野党は政権担当能力がないのか",
    "thread_id": "1769215160"
  },
  {
    "title": "【話題】名古屋は東日本か、西日本かで大激論。関東人西日本でしょ？関西人いや東やろ",
    "thread_id": "1769258273"
  },
  {
    "title": "店で出てくる温かいおしぼりで顔と脇をふいて鼻をかむケンモメン",
    "thread_id": "1769237984"
  },
  {
    "title": "【悲報】この動画、AIじゃないらしい",
    "thread_id": "1769257344"
  },
  {
    "title": "愛国者日本の中年男性を雇わずに人手不足は通らない",
    "thread_id": "1769246155"
  },
  {
    "title": "昭和生まれは知ってるが、平成生まれ以降はまったく知らない俳優天知茂竹脇無我田宮二郎ほかには？",
    "thread_id": "1769266531"
  },
  {
    "title": "ヽ´ん` ヽ´ん`ヽ´ん` 嫌儲党けんもうとうの支持母体組織",
    "thread_id": "1769185413"
  },
  {
    "title": "黒髪清楚の冷酷美少女 を助けたら、俺と二人きりの時だけデレるようになったらどうする？",
    "thread_id": "1769257226"
  },
  {
    "title": "【衆院選】新党減税日本・ゆうこく連合がガチで爆誕！原口と河村が記者会見",
    "thread_id": "1769228856"
  },
  {
    "title": "アホジャップ高裁194km/hの運転での死亡事故は危険運転致死に当たらない",
    "thread_id": "1769066413"
  },
  {
    "title": "なんで同じスレが乱立してるの？",
    "thread_id": "1769266848"
  },
  {
    "title": "明日はトライアルに行こうと思う。これは買っとけってモノある？",
    "thread_id": "1769203223"
  }
]